MANIFEST.in
setup.py
pyminiproj/__init__.py
pyminiproj/bin.py
pyminiproj/tool.sh
pyminiproj.egg-info/PKG-INFO
pyminiproj.egg-info/SOURCES.txt
pyminiproj.egg-info/dependency_links.txt
pyminiproj.egg-info/entry_points.txt
pyminiproj.egg-info/requires.txt
pyminiproj.egg-info/top_level.txt
pyminiproj/@PROJNAME@/.gitignore
pyminiproj/@PROJNAME@/.zip
pyminiproj/@PROJNAME@/LICENSE
pyminiproj/@PROJNAME@/MANIFEST.in
pyminiproj/@PROJNAME@/README.md
pyminiproj/@PROJNAME@/install.sh
pyminiproj/@PROJNAME@/install.txt
pyminiproj/@PROJNAME@/pypiupload.sh
pyminiproj/@PROJNAME@/readme.rst
pyminiproj/@PROJNAME@/setup.py
pyminiproj/@PROJNAME@/setup_ver_update.py
pyminiproj/@PROJNAME@/srch.py
pyminiproj/@PROJNAME@/uninstall.sh
pyminiproj/@PROJNAME@/updateversion.sh
pyminiproj/@PROJNAME@/BACKUP/dummy
pyminiproj/@PROJNAME@/DRAFT/dummy
pyminiproj/@PROJNAME@/INIT/credential.sh
pyminiproj/@PROJNAME@/INIT/init.sh
pyminiproj/@PROJNAME@/RESOURCES/.suffix
pyminiproj/@PROJNAME@/RESOURCES/dummy
pyminiproj/@PROJNAME@/TEST/dummy
pyminiproj/@PROJNAME@/docs/dummy
pyminiproj/@PROJNAME@/main/__init__.py
pyminiproj/@PROJNAME@/main/bin.py
pyminiproj/@PROJNAME@/main/Images/dummp
pyminiproj/@PROJNAME@/main/ReadMeDetailed/dummy